giExtract/__init__.py
giExtract/util.py
giExtract-1.0.4.data/scripts/giCube
giExtract-1.0.4.data/scripts/giExtract
giExtract-1.0.4.dist-info/LICENSE
giExtract-1.0.4.dist-info/METADATA
giExtract-1.0.4.dist-info/WHEEL
giExtract-1.0.4.dist-info/top_level.txt
giExtract-1.0.4.dist-info/RECORD
