Metadata-Version: 2.1
Name: giExtract
Version: 1.0.4
Summary: Digital pathology feature extraction
Home-page: https://github.com/caanene1/giExtract
Author: Chinedu A. Anene
Author-email: caanenedr@outlook.com
License: UNKNOWN
Download-URL: https://github.com/caanene1/giExtract/releases/download/1.0.6/giExtract-1.0.1-py3-none-any.whl
Platform: UNKNOWN
Classifier: Programming Language :: Python :: 3
Classifier: License :: OSI Approved :: MIT License
Classifier: Operating System :: OS Independent
Requires-Python: >=3.8
Requires-Dist: tensorflow (>=2.16.1)
Requires-Dist: numpy
Requires-Dist: pandas
Requires-Dist: scikit-learn (>=0.24.1)
Requires-Dist: scipy (>=1.5.4)
Requires-Dist: Pillow
Requires-Dist: opencv-python
